{
  "$schema": "https://ui.shadcn.com/schema/registry-item.json",
  "name": "autocomplete-with-label",
  "type": "registry:example",
  "description": "Autocomplete with label",
  "registryDependencies": [
    "@uitopia/autocomplete",
    "@uitopia/label"
  ],
  "files": [
    {
      "path": "registry/components/autocomplete-with-label.tsx",
      "content": "\"use client\";\n\nimport { useId } from \"react\";\n\nimport {\n  Autocomplete,\n  AutocompleteEmpty,\n  AutocompleteInput,\n  AutocompleteItem,\n  AutocompleteList,\n  AutocompletePopup,\n} from \"@/registry/ui/autocomplete\";\nimport { Label } from \"@/registry/ui/label\";\n\nconst items = [\n  { label: \"Apple\", value: \"apple\" },\n  { label: \"Banana\", value: \"banana\" },\n  { label: \"Orange\", value: \"orange\" },\n  { label: \"Grape\", value: \"grape\" },\n  { label: \"Strawberry\", value: \"strawberry\" },\n  { label: \"Mango\", value: \"mango\" },\n  { label: \"Pineapple\", value: \"pineapple\" },\n  { label: \"Kiwi\", value: \"kiwi\" },\n  { label: \"Peach\", value: \"peach\" },\n  { label: \"Pear\", value: \"pear\" },\n];\n\nexport default function AutocompleteWithLabel() {\n  const id = useId();\n  return (\n    <Autocomplete items={items}>\n      <div className=\"flex flex-col items-start gap-2\">\n        <Label htmlFor={id}>Fruits</Label>\n        <AutocompleteInput\n          id={id}\n          placeholder=\"Search items…\"\n          aria-label=\"Search items\"\n        />\n      </div>\n      <AutocompletePopup>\n        <AutocompleteEmpty>No items found.</AutocompleteEmpty>\n        <AutocompleteList>\n          {(item) => (\n            <AutocompleteItem key={item.value} value={item}>\n              {item.label}\n            </AutocompleteItem>\n          )}\n        </AutocompleteList>\n      </AutocompletePopup>\n    </Autocomplete>\n  );\n}\n",
      "type": "registry:example"
    }
  ],
  "categories": [
    "autocomplete",
    "input"
  ]
}